FPGA/FPGA_02_adder/halfadder.v
// half-adder

module half_tasizan (A, B, C, S);

    input A, B; // inputs
    output C, S; // outputs

    assign C = A & B; // carry output
    assign S = A ^ B; // sum output

endmodule

FPGA/FPGA_02_adder/fulladder.v
// full-adder
module full_tasizan (A, B, Cin, Cout, S);
    input A, B, Cin; // inputs
    output Cout, S; // outputs
    wire C0, S0, C1; // intermediate wires (Do not use resister instead of wire)

    half_tasizan ha0(A, B, C0, S0); // first half-adder
    half_tasizan ha1(S0, Cin, C1, S); // second half-adder

    assign Cout = C0 | C1; // final carry output (Cout) is the OR of the two carry outputs (C0 and C1)
endmodule

FPGA/FPGA_02/fulladder_test.v
// simulation of full_tasizan
// first, we need to determine the timescale for the simulation
`timescale 1ns / 1ps // time unit is 1ns, time precision is 1ps (precision = marume_gosa)

module full_tasizan_test; // testbench module

    reg a, b, cin; // inputs are declared as registers
    wire cout, s; // outputs are declared as wires

    parameter STEP = 100; // time step for each test case

    full_tasizan tashichan(a, b, cin, cout, s); // instantiate the half_tasizan module

    initial begin
        a = 1'b0; b = 1'b0; cin = 1'b0; // initialize inputs
        #STEP; // wait for STEP time
        a = 1'b0; b = 1'b0; cin = 1'b1;// test case 1
        #STEP;
        a = 1'b0; b = 1'b1; cin = 1'b0;// test case 2
        #STEP;
        a = 1'b0; b = 1'b1; cin = 1'b1;// test case 3
        #STEP;
        a = 1'b1; b = 1'b0; cin = 1'b0; // test case 4
        #STEP; // wait for STEP time
        a = 1'b1; b = 1'b0; cin = 1'b1;// test case 5
        #STEP;
        a = 1'b1; b = 1'b1; cin = 1'b0;// test case 6
        #STEP;
        a = 1'b1; b = 1'b1; cin = 1'b1;// test case 7
        #STEP;
        $finish; // end the simulation
    end

    initial begin // monitoring test results (Following codes are like spells)
        $monitor($stime, " a=%b b=%b cin=%b cout=%b s=%b", a, b, cin, cout, s); // print the values of inputs and outputs
        $dumpfile("fulladder_test.vcd"); // create a VCD file for waveform viewing
        $dumpvars(0, full_tasizan_test); // dump all variables in the testbench
    end

endmodule

FPGA/FPGA_02/fulladder_test.vcd
$date
	Wed Apr 30 04:58:04 2025
$end
$version
	Icarus Verilog
$end
$timescale
	1ps
$end
$scope module full_tasizan_test $end
$var wire 1 ! s $end
$var wire 1 " cout $end
$var parameter 32 # STEP $end
$var reg 1 $ a $end
$var reg 1 % b $end
$var reg 1 & cin $end
$scope module tashichan $end
$var wire 1 $ A $end
$var wire 1 % B $end
$var wire 1 & Cin $end
$var wire 1 " Cout $end
$var wire 1 ' S0 $end
$var wire 1 ! S $end
$var wire 1 ( C1 $end
$var wire 1 ) C0 $end
$scope module ha0 $end
$var wire 1 $ A $end
$var wire 1 % B $end
$var wire 1 ) C $end
$var wire 1 ' S $end
$upscope $end
$scope module ha1 $end
$var wire 1 ' A $end
$var wire 1 & B $end
$var wire 1 ( C $end
$var wire 1 ! S $end
$upscope $end
$upscope $end
$upscope $end
$enddefinitions $end
$comment Show the parameter values. $end
$dumpall
b1100100 #
$end
#0
$dumpvars
0)
0(
0'
0&
0%
0$
0"
0!
$end
#100000
1!
1&
#200000
1'
0&
1%
#300000
1"
1(
0!
1&
#400000
0"
0(
1!
0&
0%
1$
#500000
1"
1(
0!
1&
#600000
0(
1)
0'
0&
1%
#700000
1!
1&
