FPGA/FPGA_03_counter/dff.v
// D-flipflop

module dff(CLK, RST, D, Q);

    input CLK, RST, D; // inputs: clock, reset, data
    output Q; // output: data output
    reg Q; // output is declared as a register
    // Q is set as reg because DFF refer to the previous value of Q

    always @(posedge CLK or negedge RST) begin // on rising edge of clock or reset
        if (RST == 1'b0) begin
            Q <= 1'b0; // you can assign 1'b0 because Q is reg
        end else begin
            Q <= D;
        end
    end

endmodule

FPGA/FPGA_03_counter/dff4bit.v
// dff 4bit

module dff4bit(clk, rst, d, q);
    input clk, rst; // inputs: clock and reset
    input [3:0] d; // 4-bit data input
    output [3:0] q; // 4-bit data output
    // in this case, q is declared as a wire, not a reg
    // because "Q" as registers are hidden inside the dff module

    dff dff0(clk, rst, d[0], q[0]); // instantiate 4 D flip-flops for each bit of the input
    dff dff1(clk, rst, d[1], q[1]);
    dff dff2(clk, rst, d[2], q[2]);
    dff dff3(clk, rst, d[3], q[3]);


endmodule

FPGA/FPGA_03/counter10.v
// countrer 10

module counter10(clk, rst, cnt);

    input clk, rst; // input signals
    output [3:0] cnt; // 4-bit output signal
    // this "cnt" is wire

    wire [3:0] d, q;

    function [3:0] incr;

        input [3:0] invar;
            case (invar)
                4'h0: incr = 4'h1;
                4'h1: incr = 4'h2;
                4'h2: incr = 4'h3;
                4'h3: incr = 4'h4;
                4'h4: incr = 4'h5;
                4'h5: incr = 4'h6;
                4'h6: incr = 4'h7;
                4'h7: incr = 4'h8;
                4'h8: incr = 4'h9;
                4'h9: incr = 4'ha;
                default : incr = 4'h0; // reset to 0 if input is not in the range
            endcase

    endfunction

    assign d = incr(q); // increment the value of q using the incr function

    dff4bit dff4_0(clk, rst, d, q);

    assign cnt = q;

endmodule

FPGA/FPGA_03/counter10_test.v
// counter10 simulation
`timescale 1ns/1ps

module counter10_test;

    reg clk, rst;
    // reg [3:0] d; // 4-bit data input
    wire [3:0] cnt; // this "q" is wire, and "Q" is reg in dff module

    parameter STEP = 1000; // time step for each test case

    // dff4bit dff4_0(clk, rst, d, q); // instantiate the dff module
    counter10 counter10_0(clk, rst, cnt); // instantiate the counter10 module

    always begin // clock generation
        clk = 1'b0;
        #(STEP/2);
        clk = 1'b1;
        #(STEP/2);
        // forever #STEP clk = ~clk; // this explanation is smarter
    end

    initial begin
        rst = 1'b1;
        #(STEP/4) rst = 0;
        #STEP; rst = 1'b1;
        #(STEP*15);
        $finish;
    end

    initial begin
        $monitor($stime, "clk=%b rst=%b cnt=%h", clk, rst, cnt); // print the values of inputs and outputs
        $dumpfile("coutner10.vcd"); // create a VCD file for waveform viewing
        $dumpvars(0, counter10_test); // dump all variables in the testbench
    end

endmodule

FPGA/FPGA_03/coutner10.vcd
$date
	Sat May 03 17:47:50 2025
$end
$version
	Icarus Verilog
$end
$timescale
	1ps
$end
$scope module counter10_test $end
$var wire 4 ! cnt [3:0] $end
$var parameter 32 " STEP $end
$var reg 1 # clk $end
$var reg 1 $ rst $end
$scope module counter10_0 $end
$var wire 1 # clk $end
$var wire 4 % cnt [3:0] $end
$var wire 1 $ rst $end
$var wire 4 & q [3:0] $end
$var wire 4 ' d [3:0] $end
$scope function incr $end
$var reg 4 ( invar [3:0] $end
$upscope $end
$scope module dff4_0 $end
$var wire 1 # clk $end
$var wire 4 ) d [3:0] $end
$var wire 1 $ rst $end
$var wire 4 * q [3:0] $end
$scope module dff0 $end
$var wire 1 # CLK $end
$var wire 1 + D $end
$var wire 1 $ RST $end
$var reg 1 , Q $end
$upscope $end
$scope module dff1 $end
$var wire 1 # CLK $end
$var wire 1 - D $end
$var wire 1 $ RST $end
$var reg 1 . Q $end
$upscope $end
$scope module dff2 $end
$var wire 1 # CLK $end
$var wire 1 / D $end
$var wire 1 $ RST $end
$var reg 1 0 Q $end
$upscope $end
$scope module dff3 $end
$var wire 1 # CLK $end
$var wire 1 1 D $end
$var wire 1 $ RST $end
$var reg 1 2 Q $end
$upscope $end
$upscope $end
$upscope $end
$upscope $end
$enddefinitions $end
$comment Show the parameter values. $end
$dumpall
b1111101000 "
$end
#0
$dumpvars
x2
01
x0
0/
x.
0-
x,
0+
bx *
b0 )
bx (
b0 '
bx &
bx %
1$
0#
bx !
$end
#250000
1+
b1 '
b1 )
b0 (
0,
0.
00
b0 !
b0 %
b0 &
b0 *
02
0$
#500000
1#
#1000000
0#
#1250000
1$
#1500000
0+
1-
b10 '
b10 )
b1 (
b1 !
b1 %
b1 &
b1 *
1,
1#
#2000000
0#
#2500000
1+
b11 '
b11 )
b10 (
1.
b10 !
b10 %
b10 &
b10 *
0,
1#
#3000000
0#
#3500000
0+
0-
1/
b100 '
b100 )
b11 (
b11 !
b11 %
b11 &
b11 *
1,
1#
#4000000
0#
#4500000
1+
b101 '
b101 )
b100 (
10
0.
b100 !
b100 %
b100 &
b100 *
0,
1#
#5000000
0#
#5500000
0+
1-
b110 '
b110 )
b101 (
b101 !
b101 %
b101 &
b101 *
1,
1#
#6000000
0#
#6500000
1+
b111 '
b111 )
b110 (
1.
b110 !
b110 %
b110 &
b110 *
0,
1#
#7000000
0#
#7500000
0+
0-
0/
11
b1000 '
b1000 )
b111 (
b111 !
b111 %
b111 &
b111 *
1,
1#
#8000000
0#
#8500000
1+
b1001 '
b1001 )
b1000 (
12
00
0.
b1000 !
b1000 %
b1000 &
b1000 *
0,
1#
#9000000
0#
#9500000
0+
1-
b1010 '
b1010 )
b1001 (
b1001 !
b1001 %
b1001 &
b1001 *
1,
1#
#10000000
0#
#10500000
0-
01
b0 '
b0 )
b1010 (
1.
b1010 !
b1010 %
b1010 &
b1010 *
0,
1#
#11000000
0#
#11500000
1+
b1 '
b1 )
b0 (
0.
b0 !
b0 %
b0 &
b0 *
02
1#
#12000000
0#
#12500000
0+
1-
b10 '
b10 )
b1 (
b1 !
b1 %
b1 &
b1 *
1,
1#
#13000000
0#
#13500000
1+
b11 '
b11 )
b10 (
0,
b10 !
b10 %
b10 &
b10 *
1.
1#
#14000000
0#
#14500000
0+
0-
1/
b100 '
b100 )
b11 (
b11 !
b11 %
b11 &
b11 *
1,
1#
#15000000
0#
#15500000
1+
b101 '
b101 )
b100 (
0,
0.
b100 !
b100 %
b100 &
b100 *
10
1#
