FPGA/FPGA_03_counter/dff.v
// D-flipflop

module dff(CLK, RST, D, Q);

    input CLK, RST, D; // inputs: clock, reset, data
    output Q; // output: data output
    reg Q; // output is declared as a register
    // Q is set as reg because DFF refer to the previous value of Q

    always @(posedge CLK or negedge RST) begin // on rising edge of clock or reset
        if (RST == 1'b0) begin
            Q <= 1'b0; // you can assign 1'b0 because Q is reg
        end else begin
            Q <= D;
        end
    end

endmodule

DigitalTraining/FPGA/FPGA_03_counter/dff_test.v
// dff simulation
`timescale 1ns/1ps

module dff_test;

    reg clk, rst;
    reg d;
    wire q; // this "q" is wire, and "Q" is reg in dff module

    parameter STEP = 1000; // time step for each test case

    dff dff0(clk, rst, d, q); // instantiate the dff module

    always begin // clock generation
        clk = 1'b0;
        #(STEP/2);
        clk = 1'b1;
        #(STEP/2);
        // forever #STEP clk = ~clk; // this explanation is smarter
    end

    initial begin
        rst = 1'b1; d = 1'b1;
        #(STEP/4) rst = 0;
        #STEP; rst = 1'b1;
        #(STEP*1.1) d = 1;
        #(STEP*2.1) d = 0;
        #(STEP*3.1) d = 1;
        #(STEP*4.1) d = 0;
        #(STEP*2);
        $finish;
    end

    initial begin
        $monitor($stime, "clk=%b rst=%b d=%b q=%b", clk, rst, d, q); // print the values of inputs and outputs
        $dumpfile("dff.vcd"); // create a VCD file for waveform viewing
        $dumpvars(0, dff_test); // dump all variables in the testbench
    end

endmodule

FPGA/FPGA_03/dff.vcd
$date
	Wed Apr 30 06:46:55 2025
$end
$version
	Icarus Verilog
$end
$timescale
	1ps
$end
$scope module dff_test $end
$var wire 1 ! q $end
$var parameter 32 " STEP $end
$var reg 1 # clk $end
$var reg 1 $ d $end
$var reg 1 % rst $end
$scope module dff0 $end
$var wire 1 # CLK $end
$var wire 1 $ D $end
$var wire 1 % RST $end
$var reg 1 ! Q $end
$upscope $end
$upscope $end
$enddefinitions $end
$comment Show the parameter values. $end
$dumpall
b1111101000 "
$end
#0
$dumpvars
1%
1$
0#
x!
$end
#250000
0!
0%
#500000
1#
#1000000
0#
#1250000
1%
#1500000
1!
1#
#2000000
0#
#2500000
1#
#3000000
0#
#3500000
1#
#4000000
0#
#4450000
0$
#4500000
0!
1#
#5000000
0#
#5500000
1#
#6000000
0#
#6500000
1#
#7000000
0#
#7500000
1#
#7550000
1$
#8000000
0#
#8500000
1!
1#
#9000000
0#
#9500000
1#
#10000000
0#
#10500000
1#
#11000000
0#
#11500000
1#
#11650000
0$
#12000000
0#
#12500000
0!
1#
