FPGA/FPGA_03_counter/dff.v
// D-flipflop

module dff(CLK, RST, D, Q);

    input CLK, RST, D; // inputs: clock, reset, data
    output Q; // output: data output
    reg Q; // output is declared as a register
    // Q is set as reg because DFF refer to the previous value of Q

    always @(posedge CLK or negedge RST) begin // on rising edge of clock or reset
        if (RST == 1'b0) begin
            Q <= 1'b0; // you can assign 1'b0 because Q is reg
        end else begin
            Q <= D;
        end
    end

endmodule

FPGA/FPGA_03_counter/dff4bit.v
// dff 4bit

module dff4bit(clk, rst, d, q);
    input clk, rst; // inputs: clock and reset
    input [3:0] d; // 4-bit data input
    output [3:0] q; // 4-bit data output
    // in this case, q is declared as a wire, not a reg
    // because "Q" as registers are hidden inside the dff module

    dff dff0(clk, rst, d[0], q[0]); // instantiate 4 D flip-flops for each bit of the input
    dff dff1(clk, rst, d[1], q[1]);
    dff dff2(clk, rst, d[2], q[2]);
    dff dff3(clk, rst, d[3], q[3]);


endmodule

DigitalTraining/FPGA/FPGA_03_counter/dff4bit_test.v
// dff simulation
`timescale 1ns/1ps

module dff4bit_test;

    reg clk, rst;
    reg [3:0] d; // 4-bit data input
    wire [3:0] q; // this "q" is wire, and "Q" is reg in dff module

    parameter STEP = 1000; // time step for each test case

    dff4bit dff4_0(clk, rst, d, q); // instantiate the dff module

    always begin // clock generation
        clk = 1'b0;
        #(STEP/2);
        clk = 1'b1;
        #(STEP/2);
        // forever #STEP clk = ~clk; // this explanation is smarter
    end

    initial begin
        rst = 1'b1; d = 4'h1;
        #(STEP/4) rst = 0;
        #STEP; rst = 1'b1;
        #(STEP*1.1) d = 4'h3;
        #(STEP*2.1) d = 4'hc;
        #(STEP*3.1) d = 4'h9;
        #(STEP*4.1) d = 4'h0;
        #(STEP*2);
        $finish;
    end

    initial begin
        $monitor($stime, "clk=%b rst=%b d=%h q=%h", clk, rst, d, q); // print the values of inputs and outputs
        $dumpfile("dff4bit.vcd"); // create a VCD file for waveform viewing
        $dumpvars(0, dff4bit_test); // dump all variables in the testbench
    end

endmodule

FPGA/FPGA_03/dff4bit.vcd
$date
	Wed Apr 30 16:34:39 2025
$end
$version
	Icarus Verilog
$end
$timescale
	1ps
$end
$scope module dff4bit_test $end
$var wire 4 ! q [3:0] $end
$var parameter 32 " STEP $end
$var reg 1 # clk $end
$var reg 4 $ d [3:0] $end
$var reg 1 % rst $end
$scope module dff4_0 $end
$var wire 1 # clk $end
$var wire 4 & d [3:0] $end
$var wire 1 % rst $end
$var wire 4 ' q [3:0] $end
$scope module dff0 $end
$var wire 1 # CLK $end
$var wire 1 ( D $end
$var wire 1 % RST $end
$var reg 1 ) Q $end
$upscope $end
$scope module dff1 $end
$var wire 1 # CLK $end
$var wire 1 * D $end
$var wire 1 % RST $end
$var reg 1 + Q $end
$upscope $end
$scope module dff2 $end
$var wire 1 # CLK $end
$var wire 1 , D $end
$var wire 1 % RST $end
$var reg 1 - Q $end
$upscope $end
$scope module dff3 $end
$var wire 1 # CLK $end
$var wire 1 . D $end
$var wire 1 % RST $end
$var reg 1 / Q $end
$upscope $end
$upscope $end
$upscope $end
$enddefinitions $end
$comment Show the parameter values. $end
$dumpall
b1111101000 "
$end
#0
$dumpvars
x/
0.
x-
0,
x+
0*
x)
1(
bx '
b1 &
1%
b1 $
0#
bx !
$end
#250000
0)
0+
0-
b0 !
b0 '
0/
0%
#500000
1#
#1000000
0#
#1250000
1%
#1500000
b1 !
b1 '
1)
1#
#2000000
0#
#2350000
1*
b11 $
b11 &
#2500000
b11 !
b11 '
1+
1#
#3000000
0#
#3500000
1#
#4000000
0#
#4450000
0(
0*
1,
1.
b1100 $
b1100 &
#4500000
1/
1-
0+
b1100 !
b1100 '
0)
1#
#5000000
0#
#5500000
1#
#6000000
0#
#6500000
1#
#7000000
0#
#7500000
1#
#7550000
1(
0,
b1001 $
b1001 &
#8000000
0#
#8500000
0-
b1001 !
b1001 '
1)
1#
#9000000
0#
#9500000
1#
#10000000
0#
#10500000
1#
#11000000
0#
#11500000
1#
#11650000
0(
0.
b0 $
b0 &
#12000000
0#
#12500000
0/
b0 !
b0 '
0)
1#
